kotsu/__init__.py
kotsu/error.py
kotsu/registration.py
kotsu/run.py
kotsu/store.py
kotsu/typing.py
kotsu-0.4.0.dist-info/licenses/LICENSE.txt
kotsu-0.4.0.dist-info/METADATA
kotsu-0.4.0.dist-info/WHEEL
kotsu-0.4.0.dist-info/top_level.txt
kotsu-0.4.0.dist-info/RECORD
