Metadata-Version: 2.4
Name: kotsu
Version: 0.4.0
Summary: Lightweight framework for structured and repeatable model validation
Author-email: datavaluepeople <opensource@datavaluepeople.com>
License-Expression: MIT
Project-URL: Homepage, https://github.com/datavaluepeople/kotsu
Project-URL: Repository, https://github.com/datavaluepeople/kotsu
Classifier: Programming Language :: Python :: 3
Classifier: Programming Language :: Python :: 3.9
Classifier: Programming Language :: Python :: 3.10
Classifier: Programming Language :: Python :: 3.11
Classifier: Programming Language :: Python :: 3.12
Requires-Python: >=3.9
License-File: LICENSE.txt
Requires-Dist: pandas
Requires-Dist: typing_extensions
Dynamic: license-file
